promptsmith/__init__.py
promptsmith/client.py
promptsmith/src/models.py
promptsmith-0.1.0.dist-info/METADATA
promptsmith-0.1.0.dist-info/WHEEL
promptsmith-0.1.0.dist-info/RECORD
