Metadata-Version: 2.1
Name: promptsmith
Version: 0.1.0
Summary: 
Author: Farouk Charkas
Author-email: farouk.charkas@gmail.com
Requires-Python: >=3.12,<4.0
Classifier: Programming Language :: Python :: 3
Classifier: Programming Language :: Python :: 3.12
Requires-Dist: ipykernel (>=6.29.5,<7.0.0)
